eilof/__init__.py
eilof/eilof_model.py
eilof/utils.py
eilof-1.0.1.dist-info/LICENSE
eilof-1.0.1.dist-info/METADATA
eilof-1.0.1.dist-info/WHEEL
eilof-1.0.1.dist-info/top_level.txt
eilof-1.0.1.dist-info/RECORD
