Metadata-Version: 2.1
Name: eilof
Version: 1.0.1
Summary: Efficient implementation of Incremental Local Outlier Factor (EILOF).
Home-page: https://github.com/Lucchh/eilof
Author: Rui Hu, Luc (Zhilu) Chen, Yiwei Wang
Author-email: rui.hu@csusb.edu, luchen@g.harvard.edu, yiweiw@ucr.edu
Project-URL: Documentation, https://github.com/Lucchh/eilof#readme
Project-URL: Source, https://github.com/Lucchh/eilof
Project-URL: Tracker, https://github.com/Lucchh/eilof/issues
Project-URL: GitHub Statistics, https://github.com/Lucchh/eilof
Classifier: Programming Language :: Python :: 3
Classifier: License :: OSI Approved :: MIT License
Classifier: Operating System :: OS Independent
Classifier: Topic :: Scientific/Engineering :: Artificial Intelligence
Classifier: Topic :: Scientific/Engineering :: Information Analysis
Classifier: Topic :: Software Development :: Libraries :: Python Modules
Classifier: Intended Audience :: Science/Research
Classifier: Natural Language :: English
Requires-Python: >=3.8
License-File: LICENSE
Requires-Dist: numpy<2.0.0,>=1.19.5
Requires-Dist: scipy<2.0.0,>=1.6.0
Requires-Dist: matplotlib<4.0.0,>=3.3.4
Requires-Dist: seaborn<1.0.0,>=0.9.0
Requires-Dist: scikit-learn<2.0.0,>=1.0.0
